{
  "generalInfo": {
    "title": "Загальна інформація",
    "busFares": [
      {
        "icon": "💰",
        "text": "Ціна за проїзд в автобусі — 13 грн!"
      },
      {
        "icon": "🚌",
        "text": "Ціна проїзду в 302 маршруті по Смілі — 13 грн."
      },
      {
        "icon": "🛣️",
        "text": "Ціна проїзду в 302 маршруті: До м.Черкаси — 88 грн."
      },
      {
        "icon": "💸",
        "text": "Ціна проїзду в 302 маршруті по Черкасам — 16 грн."
      }
    ],
    "privileges": [
      {
        "icon": "🎒",
        "text": "Діти до 7 років — безкоштовно"
      },
      {
        "icon": "🎖️",
        "text": "Інваліди війни"
      },
      {
        "icon": "🛡️",
        "text": "Учасники бойових дій"
      },
      {
        "icon": "♿",
        "text": "Інваліди 1 категорії"
      },
      {
        "icon": "👧",
        "text": "Діти-інваліди"
      },
      {
        "icon": "🧑‍🦱",
        "text": "Діти-сироти"
      },
      {
        "icon": "🏅",
        "text": "Ветерани АТО, ООС, повномасштабної війни (УБД), Афганці"
      },
      {
        "icon": "👮",
        "text": "Прокуратура, поліція — по посвідченню (безкоштовно)"
      },
      {
        "icon": "☢️",
        "text": "Ліквідатори на ЧАЕС 1 категорії — безкоштовно"
      }
    ]
  },
  "poputka": {
    "title": "Попутка",
    "price": "100 грн",
    "routes": [
      {
        "city": "Сміла",
        "start": "Школа №3, Пушка",
        "end": "По вимозі, Літак"
      },
      {
        "city": "Черкаси",
        "start": "Літак",
        "end": "По вимозі, центр - МБК"
      }
    ],
    "links": [
      {
        "name": "Попутка.Сміла",
        "url": "https://bit.ly/3BmTmMM",
        "icon": "<i class='fa-brands fa-viber' style='color: #7360f2; font-size: 1.4em;'></i>"
      },
      {
        "name": "Попутка.Сміла",
        "url": "https://t.me/PopytkaSmila",
        "icon": "<i class='fa-brands fa-telegram' style='color: #24A1DE; font-size: 1.4em;'></i>"
      },
      {
        "name": "Попутка.Черкаси",
        "url": "https://t.me/telecar_cherkassy_geo",
        "icon": "<i class='fa-brands fa-telegram' style='color: #24A1DE; font-size: 1.4em;'></i>"
      }
    ]
  }
}